{
  "type": "REACT_COMPONENT",
  "name": "Fade",
  "description": "",
  "schema": {
    "selection": "anyOf",
    "types": [
      {
        "type": "FadeProps"
      }
    ],
    "props": [
      {
        "category": "STYLE_LAYOUT",
        "name": "className",
        "isRequired": false,
        "isDeprecated": false,
        "schema": {
          "selection": "anyOf",
          "types": [
            {
              "type": "LABEL",
              "value": "STRING"
            }
          ]
        },
        "description": "",
        "defaultValue": {
          "type": "CUSTOM",
          "value": ""
        },
        "id": "42fc75d4_5da4_44a3_a8c8_576022f8279e"
      },
      {
        "category": "BEHAVIOR_STATE",
        "name": "in",
        "isRequired": false,
        "isDeprecated": false,
        "schema": {
          "selection": "anyOf",
          "types": [
            {
              "type": "LABEL",
              "value": "BOOLEAN"
            }
          ]
        },
        "description": "",
        "defaultValue": {
          "type": "CUSTOM",
          "value": ""
        },
        "id": "0b950aa5_9610_45ae_bb8f_a440f2fa0a73"
      },
      {
        "category": "OTHERS",
        "name": "mountOnEnter",
        "isRequired": false,
        "isDeprecated": false,
        "schema": {
          "selection": "anyOf",
          "types": [
            {
              "type": "LABEL",
              "value": "BOOLEAN"
            }
          ]
        },
        "description": "",
        "defaultValue": {
          "type": "CUSTOM",
          "value": ""
        },
        "id": "36799504_3daa_44b5_8df3_1e774a45cbe5"
      },
      {
        "category": "OTHERS",
        "name": "unmountOnExit",
        "isRequired": false,
        "isDeprecated": false,
        "schema": {
          "selection": "anyOf",
          "types": [
            {
              "type": "LABEL",
              "value": "BOOLEAN"
            }
          ]
        },
        "description": "",
        "defaultValue": {
          "type": "CUSTOM",
          "value": ""
        },
        "id": "bd244842_6c4c_48b4_9f2b_770003dec6a5"
      },
      {
        "category": "BEHAVIOR_STATE",
        "name": "appear",
        "isRequired": false,
        "isDeprecated": false,
        "schema": {
          "selection": "anyOf",
          "types": [
            {
              "type": "LABEL",
              "value": "BOOLEAN"
            }
          ]
        },
        "description": "",
        "defaultValue": {
          "type": "CUSTOM",
          "value": ""
        },
        "id": "ef76dbfb_f354_4be6_8e07_afa158c09316"
      },
      {
        "category": "ANIMATIONS_TRANSITIONS",
        "name": "timeout",
        "isRequired": false,
        "isDeprecated": false,
        "schema": {
          "selection": "anyOf",
          "types": [
            {
              "type": "LABEL",
              "value": "NUMBER"
            }
          ]
        },
        "description": "",
        "defaultValue": {
          "type": "CUSTOM",
          "value": ""
        },
        "id": "b8a769a9_a703_40b1_9cf4_75682dd34d58"
      },
      {
        "category": "CONTENT_SLOTS",
        "name": "children",
        "isRequired": true,
        "isDeprecated": false,
        "schema": {
          "selection": "anyOf",
          "types": [
            {
              "type": "UNKNOWN",
              "typeAsText": "ReactElement<unknown, string | JSXElementConstructor<any>>"
            }
          ]
        },
        "description": "",
        "defaultValue": {
          "type": "CUSTOM",
          "value": ""
        },
        "id": "c9b2ea67_05c6_4575_ad86_56e37162e80a"
      },
      {
        "category": "OTHERS",
        "name": "transitionClasses",
        "isRequired": false,
        "isDeprecated": false,
        "schema": {
          "selection": "anyOf",
          "types": [
            {
              "type": "UNKNOWN",
              "typeAsText": "Record<string, string>"
            }
          ]
        },
        "description": "",
        "defaultValue": {
          "type": "CUSTOM",
          "value": ""
        },
        "id": "113a7a83_8486_4250_bafa_7772f9af61f3"
      },
      {
        "category": "EVENTS",
        "name": "onEnter",
        "isRequired": false,
        "isDeprecated": false,
        "schema": {
          "selection": "anyOf",
          "types": [
            {
              "type": "UNKNOWN",
              "typeAsText": "(node: HTMLElement, isAppearing: boolean) => any"
            }
          ]
        },
        "description": "",
        "defaultValue": {
          "type": "CUSTOM",
          "value": ""
        },
        "id": "193dba19_e1c8_44d1_b1dc_062461ca3759"
      },
      {
        "category": "EVENTS",
        "name": "onEntering",
        "isRequired": false,
        "isDeprecated": false,
        "schema": {
          "selection": "anyOf",
          "types": [
            {
              "type": "UNKNOWN",
              "typeAsText": "(node: HTMLElement, isAppearing: boolean) => any"
            }
          ]
        },
        "description": "",
        "defaultValue": {
          "type": "CUSTOM",
          "value": ""
        },
        "id": "4a943cbd_39b7_44df_9b5f_f40a8fbadedb"
      },
      {
        "category": "EVENTS",
        "name": "onEntered",
        "isRequired": false,
        "isDeprecated": false,
        "schema": {
          "selection": "anyOf",
          "types": [
            {
              "type": "UNKNOWN",
              "typeAsText": "(node: HTMLElement, isAppearing: boolean) => any"
            }
          ]
        },
        "description": "",
        "defaultValue": {
          "type": "CUSTOM",
          "value": ""
        },
        "id": "553ab4e2_a922_493b_a0a4_78f5e9e9ee47"
      },
      {
        "category": "EVENTS",
        "name": "onExit",
        "isRequired": false,
        "isDeprecated": false,
        "schema": {
          "selection": "anyOf",
          "types": [
            {
              "type": "UNKNOWN",
              "typeAsText": "(node: HTMLElement) => any"
            }
          ]
        },
        "description": "",
        "defaultValue": {
          "type": "CUSTOM",
          "value": ""
        },
        "id": "1e7aaf8a_7f85_489b_840f_73f0b9f423c1"
      },
      {
        "category": "EVENTS",
        "name": "onExiting",
        "isRequired": false,
        "isDeprecated": false,
        "schema": {
          "selection": "anyOf",
          "types": [
            {
              "type": "UNKNOWN",
              "typeAsText": "(node: HTMLElement) => any"
            }
          ]
        },
        "description": "",
        "defaultValue": {
          "type": "CUSTOM",
          "value": ""
        },
        "id": "292a22f9_eaf2_4e4c_bb20_7208c83671e3"
      },
      {
        "category": "EVENTS",
        "name": "onExited",
        "isRequired": false,
        "isDeprecated": false,
        "schema": {
          "selection": "anyOf",
          "types": [
            {
              "type": "UNKNOWN",
              "typeAsText": "(node: HTMLElement) => any"
            }
          ]
        },
        "description": "",
        "defaultValue": {
          "type": "CUSTOM",
          "value": ""
        },
        "id": "d9f1b552_01fa_47bf_93a8_cbf037022009"
      }
    ]
  },
  "_id": "0305fdbe_e4e1_4d6e_be46_b5235f3cd46b",
  "$id": "react-bootstrap_Fade",
  "parentId": null,
  "propVars": [
    {
      "category": "STYLE_LAYOUT",
      "name": "className",
      "isRequired": false,
      "isDeprecated": false,
      "schema": {
        "selection": "anyOf",
        "types": [
          {
            "type": "UNDEFINED"
          },
          {
            "type": "STRING"
          }
        ]
      },
      "description": "",
      "defaultValue": {
        "type": "CUSTOM",
        "value": ""
      },
      "id": "42fc75d4_5da4_44a3_a8c8_576022f8279e"
    },
    {
      "category": "BEHAVIOR_STATE",
      "name": "in",
      "isRequired": false,
      "isDeprecated": false,
      "schema": {
        "selection": "anyOf",
        "types": [
          {
            "type": "UNDEFINED"
          },
          {
            "type": "BOOLEAN"
          }
        ]
      },
      "description": "",
      "defaultValue": {
        "type": "CUSTOM",
        "value": ""
      },
      "id": "0b950aa5_9610_45ae_bb8f_a440f2fa0a73"
    },
    {
      "category": "OTHERS",
      "name": "mountOnEnter",
      "isRequired": false,
      "isDeprecated": false,
      "schema": {
        "selection": "anyOf",
        "types": [
          {
            "type": "UNDEFINED"
          },
          {
            "type": "BOOLEAN"
          }
        ]
      },
      "description": "",
      "defaultValue": {
        "type": "CUSTOM",
        "value": ""
      },
      "id": "36799504_3daa_44b5_8df3_1e774a45cbe5"
    },
    {
      "category": "OTHERS",
      "name": "unmountOnExit",
      "isRequired": false,
      "isDeprecated": false,
      "schema": {
        "selection": "anyOf",
        "types": [
          {
            "type": "UNDEFINED"
          },
          {
            "type": "BOOLEAN"
          }
        ]
      },
      "description": "",
      "defaultValue": {
        "type": "CUSTOM",
        "value": ""
      },
      "id": "bd244842_6c4c_48b4_9f2b_770003dec6a5"
    },
    {
      "category": "BEHAVIOR_STATE",
      "name": "appear",
      "isRequired": false,
      "isDeprecated": false,
      "schema": {
        "selection": "anyOf",
        "types": [
          {
            "type": "UNDEFINED"
          },
          {
            "type": "BOOLEAN"
          }
        ]
      },
      "description": "",
      "defaultValue": {
        "type": "CUSTOM",
        "value": ""
      },
      "id": "ef76dbfb_f354_4be6_8e07_afa158c09316"
    },
    {
      "category": "ANIMATIONS_TRANSITIONS",
      "name": "timeout",
      "isRequired": false,
      "isDeprecated": false,
      "schema": {
        "selection": "anyOf",
        "types": [
          {
            "type": "UNDEFINED"
          },
          {
            "type": "NUMBER"
          }
        ]
      },
      "description": "",
      "defaultValue": {
        "type": "CUSTOM",
        "value": ""
      },
      "id": "b8a769a9_a703_40b1_9cf4_75682dd34d58"
    },
    {
      "category": "CONTENT_SLOTS",
      "name": "children",
      "isRequired": true,
      "isDeprecated": false,
      "schema": {
        "selection": "anyOf",
        "types": [
          {
            "type": "UNKNOWN",
            "typeAsText": "ReactElement<unknown, string | JSXElementConstructor<any>>"
          }
        ]
      },
      "description": "",
      "defaultValue": {
        "type": "CUSTOM",
        "value": ""
      },
      "id": "c9b2ea67_05c6_4575_ad86_56e37162e80a"
    },
    {
      "category": "OTHERS",
      "name": "transitionClasses",
      "isRequired": false,
      "isDeprecated": false,
      "schema": {
        "selection": "anyOf",
        "types": [
          {
            "type": "UNDEFINED"
          },
          {
            "type": "UNKNOWN",
            "typeAsText": "Record<string, string>"
          }
        ]
      },
      "description": "",
      "defaultValue": {
        "type": "CUSTOM",
        "value": ""
      },
      "id": "113a7a83_8486_4250_bafa_7772f9af61f3"
    },
    {
      "category": "EVENTS",
      "name": "onEnter",
      "isRequired": false,
      "isDeprecated": false,
      "schema": {
        "selection": "anyOf",
        "types": [
          {
            "type": "UNDEFINED"
          },
          {
            "type": "FUNCTION",
            "value": "(node: HTMLElement, isAppearing: boolean) => any",
            "parameters": [
              {
                "name": "node",
                "schema": {
                  "selection": "anyOf",
                  "types": [
                    {
                      "type": "UNKNOWN",
                      "typeAsText": "HTMLElement"
                    }
                  ]
                }
              },
              {
                "name": "isAppearing",
                "schema": {
                  "selection": "anyOf",
                  "types": [
                    {
                      "type": "BOOLEAN"
                    },
                    {
                      "type": "BOOLEAN"
                    }
                  ]
                }
              }
            ]
          }
        ]
      },
      "description": "",
      "defaultValue": {
        "type": "CUSTOM",
        "value": ""
      },
      "id": "193dba19_e1c8_44d1_b1dc_062461ca3759"
    },
    {
      "category": "EVENTS",
      "name": "onEntering",
      "isRequired": false,
      "isDeprecated": false,
      "schema": {
        "selection": "anyOf",
        "types": [
          {
            "type": "UNDEFINED"
          },
          {
            "type": "FUNCTION",
            "value": "(node: HTMLElement, isAppearing: boolean) => any",
            "parameters": [
              {
                "name": "node",
                "schema": {
                  "selection": "anyOf",
                  "types": [
                    {
                      "type": "UNKNOWN",
                      "typeAsText": "HTMLElement"
                    }
                  ]
                }
              },
              {
                "name": "isAppearing",
                "schema": {
                  "selection": "anyOf",
                  "types": [
                    {
                      "type": "BOOLEAN"
                    },
                    {
                      "type": "BOOLEAN"
                    }
                  ]
                }
              }
            ]
          }
        ]
      },
      "description": "",
      "defaultValue": {
        "type": "CUSTOM",
        "value": ""
      },
      "id": "4a943cbd_39b7_44df_9b5f_f40a8fbadedb"
    },
    {
      "category": "EVENTS",
      "name": "onEntered",
      "isRequired": false,
      "isDeprecated": false,
      "schema": {
        "selection": "anyOf",
        "types": [
          {
            "type": "UNDEFINED"
          },
          {
            "type": "FUNCTION",
            "value": "(node: HTMLElement, isAppearing: boolean) => any",
            "parameters": [
              {
                "name": "node",
                "schema": {
                  "selection": "anyOf",
                  "types": [
                    {
                      "type": "UNKNOWN",
                      "typeAsText": "HTMLElement"
                    }
                  ]
                }
              },
              {
                "name": "isAppearing",
                "schema": {
                  "selection": "anyOf",
                  "types": [
                    {
                      "type": "BOOLEAN"
                    },
                    {
                      "type": "BOOLEAN"
                    }
                  ]
                }
              }
            ]
          }
        ]
      },
      "description": "",
      "defaultValue": {
        "type": "CUSTOM",
        "value": ""
      },
      "id": "553ab4e2_a922_493b_a0a4_78f5e9e9ee47"
    },
    {
      "category": "EVENTS",
      "name": "onExit",
      "isRequired": false,
      "isDeprecated": false,
      "schema": {
        "selection": "anyOf",
        "types": [
          {
            "type": "UNDEFINED"
          },
          {
            "type": "FUNCTION",
            "value": "(node: HTMLElement) => any",
            "parameters": [
              {
                "name": "node",
                "schema": {
                  "selection": "anyOf",
                  "types": [
                    {
                      "type": "UNKNOWN",
                      "typeAsText": "HTMLElement"
                    }
                  ]
                }
              }
            ]
          }
        ]
      },
      "description": "",
      "defaultValue": {
        "type": "CUSTOM",
        "value": ""
      },
      "id": "1e7aaf8a_7f85_489b_840f_73f0b9f423c1"
    },
    {
      "category": "EVENTS",
      "name": "onExiting",
      "isRequired": false,
      "isDeprecated": false,
      "schema": {
        "selection": "anyOf",
        "types": [
          {
            "type": "UNDEFINED"
          },
          {
            "type": "FUNCTION",
            "value": "(node: HTMLElement) => any",
            "parameters": [
              {
                "name": "node",
                "schema": {
                  "selection": "anyOf",
                  "types": [
                    {
                      "type": "UNKNOWN",
                      "typeAsText": "HTMLElement"
                    }
                  ]
                }
              }
            ]
          }
        ]
      },
      "description": "",
      "defaultValue": {
        "type": "CUSTOM",
        "value": ""
      },
      "id": "292a22f9_eaf2_4e4c_bb20_7208c83671e3"
    },
    {
      "category": "EVENTS",
      "name": "onExited",
      "isRequired": false,
      "isDeprecated": false,
      "schema": {
        "selection": "anyOf",
        "types": [
          {
            "type": "UNDEFINED"
          },
          {
            "type": "FUNCTION",
            "value": "(node: HTMLElement) => any",
            "parameters": [
              {
                "name": "node",
                "schema": {
                  "selection": "anyOf",
                  "types": [
                    {
                      "type": "UNKNOWN",
                      "typeAsText": "HTMLElement"
                    }
                  ]
                }
              }
            ]
          }
        ]
      },
      "description": "",
      "defaultValue": {
        "type": "CUSTOM",
        "value": ""
      },
      "id": "d9f1b552_01fa_47bf_93a8_cbf037022009"
    }
  ],
  "isMostUsed": false
}